{
"items":[
  {
    "id": 118903,
    "address": "1311 W CENTURY BLVD",
    "city": "Nazlini",
    "DOB": "1988-12-08T22:11:38Z",
    "sex": "F",
    "latitude": 36,
    "name": "BRODIE,STEPHAN A",
    "state": "Arizona",
    "email": "",
    "longitude": -109,
    "EMPLOYMENT_STATUS": "Unemployed",
    "collection_id": "V_Participant_detail",
    "PEOPLE_COVERED": 1,
    "OPTIONAL_INSURED": 500000,
    "ANNUAL_INCOME": 100000,
    "MARITAL_STATUS": "S",
    "HEIGHT": 62,
    "WEIGHT": 273,
    "TOBACCO": "No",
    "GOLD": 96,
    "BRONZE": 31,
    "SILVER": 57,
    "PLATINUM": 148,
    "PURCHASED": "Silver"
  },
  {
    "id": 118904,
    "address": "2701 SHARONDELL DR",
    "city": "Red Valley",
    "DOB": "1990-06-08T22:11:38Z",
    "sex": "M",
    "latitude": 35,
    "name": "WIEDERHOLT,MARICOR T",
    "state": "Arizona",
    "email": "",
    "longitude": -110,
    "EMPLOYMENT_STATUS": "Unemployed",
    "collection_id": "V_Participant_detail",
    "PEOPLE_COVERED": 2,
    "OPTIONAL_INSURED": 700000,
    "ANNUAL_INCOME": 100000,
    "MARITAL_STATUS": "S",
    "HEIGHT": 55,
    "WEIGHT": 154,
    "TOBACCO": "No",
    "GOLD": 106,
    "BRONZE": 41,
    "SILVER": 67,
    "PLATINUM": 158,
    "PURCHASED": "Silver"
  },
  {
    "id": 118909,
    "address": "669 GROVE STREET #C",
    "city": "Bisbee",
    "DOB": "1991-06-08T22:11:38Z",
    "sex": "F",
    "latitude": 31,
    "name": "FRATIS,KEYWUN W",
    "state": "Arizona",
    "email": "",
    "longitude": -110,
    "EMPLOYMENT_STATUS": "Unemployed",
    "collection_id": "V_Participant_detail",
    "PEOPLE_COVERED": 2,
    "OPTIONAL_INSURED": 700000,
    "ANNUAL_INCOME": 100000,
    "MARITAL_STATUS": "M",
    "HEIGHT": 75,
    "WEIGHT": 283,
    "TOBACCO": "Yes",
    "GOLD": 122,
    "BRONZE": 57,
    "SILVER": 83,
    "PLATINUM": 174,
    "PURCHASED": "Silver"
  },
  {
    "id": 118918,
    "address": "451 23RD AVE #A",
    "city": "Huachuca City",
    "DOB": "1989-06-08T22:11:38Z",
    "sex": "M",
    "latitude": 32,
    "name": "WEEKS KAREN S.,DOSHANEY",
    "state": "Arizona",
    "email": "john@antiquevideo.com",
    "longitude": -110,
    "EMPLOYMENT_STATUS": "Unemployed",
    "collection_id": "V_Participant_detail",
    "PEOPLE_COVERED": 1,
    "OPTIONAL_INSURED": 500000,
    "ANNUAL_INCOME": 100000,
    "MARITAL_STATUS": "M",
    "HEIGHT": 66,
    "WEIGHT": 136,
    "TOBACCO": "No",
    "GOLD": 96,
    "BRONZE": 31,
    "SILVER": 57,
    "PLATINUM": 148,
    "PURCHASED": "Silver"
  },
  {
    "id": 118924,
    "address": "602 GLENN AVE,5153 W. BUCKEYE VIEW WY",
    "city": "Saint David",
    "DOB": "1991-09-08T22:11:38Z",
    "sex": "M",
    "latitude": 32,
    "name": "EDERRA,ALEXSIS T",
    "state": "Arizona",
    "email": "",
    "longitude": -110,
    "EMPLOYMENT_STATUS": "Unemployed",
    "collection_id": "V_Participant_detail",
    "PEOPLE_COVERED": 1,
    "OPTIONAL_INSURED": 500000,
    "ANNUAL_INCOME": 300000,
    "MARITAL_STATUS": "M",
    "HEIGHT": 63,
    "WEIGHT": 134,
    "TOBACCO": "Yes",
    "GOLD": 112,
    "BRONZE": 47,
    "SILVER": 73,
    "PLATINUM": 164,
    "PURCHASED": "Silver"
  },
  {
    "id": 118934,
    "address": "2005 CLELIA LN",
    "city": "Sierra Vista",
    "DOB": "1989-09-08T22:11:38Z",
    "sex": "M",
    "latitude": 32,
    "name": "NOTTER,JENNAFER",
    "state": "Arizona",
    "email": "",
    "longitude": -110,
    "EMPLOYMENT_STATUS": "Unemployed",
    "collection_id": "V_Participant_detail",
    "PEOPLE_COVERED": 2,
    "OPTIONAL_INSURED": 500000,
    "ANNUAL_INCOME": 100000,
    "MARITAL_STATUS": "M",
    "HEIGHT": 65,
    "WEIGHT": 176,
    "TOBACCO": "No",
    "GOLD": 96,
    "BRONZE": 31,
    "SILVER": 57,
    "PLATINUM": 148,
    "PURCHASED": "Silver"
  },
  {
    "id": 118983,
    "address": "4992 BORINA DR",
    "city": "Safford",
    "DOB": "1989-12-08T22:11:38Z",
    "sex": "F",
    "latitude": 33,
    "name": "STUCKMAN,LAYLA C",
    "state": "Arizona",
    "email": "",
    "longitude": -110,
    "EMPLOYMENT_STATUS": "Unemployed",
    "collection_id": "V_Participant_detail",
    "PEOPLE_COVERED": 2,
    "OPTIONAL_INSURED": 600000,
    "ANNUAL_INCOME": 200000,
    "MARITAL_STATUS": "M",
    "HEIGHT": 67,
    "WEIGHT": 246,
    "TOBACCO": "No",
    "GOLD": 101,
    "BRONZE": 36,
    "SILVER": 62,
    "PLATINUM": 153,
    "PURCHASED": "Gold"
  },
  {
    "id": 118993,
    "address": "2701 NORTH CO RD, WEST",
    "city": "Remer",
    "DOB": "1991-09-08T22:11:38Z",
    "sex": "F",
    "latitude": 47,
    "name": "LEEFLANG,MALANIYA J",
    "state": "Minnesota",
    "email": "",
    "longitude": -94,
    "EMPLOYMENT_STATUS": "Unemployed",
    "collection_id": "V_Participant_detail",
    "PEOPLE_COVERED": 1,
    "OPTIONAL_INSURED": 900000,
    "ANNUAL_INCOME": 300000,
    "MARITAL_STATUS": "S",
    "HEIGHT": 67,
    "WEIGHT": 106,
    "TOBACCO": "No",
    "GOLD": 106,
    "BRONZE": 41,
    "SILVER": 67,
    "PLATINUM": 158,
    "PURCHASED": "Silver"
  },
  {
    "id": 119000,
    "address": "1221 BLOSSOM HILL RD APT D-9",
    "city": "Center City",
    "DOB": "1990-05-08T22:11:38Z",
    "sex": "M",
    "latitude": 45,
    "name": "LOGAN (DUPLICATE),MACK L",
    "state": "Minnesota",
    "email": "",
    "longitude": -93,
    "EMPLOYMENT_STATUS": "Unemployed",
    "collection_id": "V_Participant_detail",
    "PEOPLE_COVERED": 1,
    "OPTIONAL_INSURED": 700000,
    "ANNUAL_INCOME": 300000,
    "MARITAL_STATUS": "M",
    "HEIGHT": 62,
    "WEIGHT": 173,
    "TOBACCO": "No",
    "GOLD": 101,
    "BRONZE": 36,
    "SILVER": 62,
    "PLATINUM": 153,
    "PURCHASED": "Silver"
  },
  {
    "id": 119002,
    "address": "6/25/08 - tlw",
    "city": "Harris",
    "DOB": "1990-02-08T22:11:38Z",
    "sex": "M",
    "latitude": 46,
    "name": "MARKIE,DESHANNA F",
    "state": "Minnesota",
    "email": "",
    "longitude": -93,
    "EMPLOYMENT_STATUS": "Unemployed",
    "collection_id": "V_Participant_detail",
    "PEOPLE_COVERED": 4,
    "OPTIONAL_INSURED": 800000,
    "ANNUAL_INCOME": 100000,
    "MARITAL_STATUS": "M",
    "HEIGHT": 61,
    "WEIGHT": 215,
    "TOBACCO": "No",
    "GOLD": 126,
    "BRONZE": 61,
    "SILVER": 87,
    "PLATINUM": 178,
    "PURCHASED": "Silver"
  },
  {
    "id": 119012,
    "address": "4175 SILVERTON ROAD NE",
    "city": "Comstock",
    "DOB": "1990-05-08T22:11:38Z",
    "sex": "M",
    "latitude": 47,
    "name": "KLEINKAUF,XINGHE F",
    "state": "Minnesota",
    "email": "",
    "longitude": -97,
    "EMPLOYMENT_STATUS": "Unemployed",
    "collection_id": "V_Participant_detail",
    "PEOPLE_COVERED": 1,
    "OPTIONAL_INSURED": 500000,
    "ANNUAL_INCOME": 300000,
    "MARITAL_STATUS": "S",
    "HEIGHT": 66,
    "WEIGHT": 106,
    "TOBACCO": "Yes",
    "GOLD": 112,
    "BRONZE": 47,
    "SILVER": 73,
    "PLATINUM": 164,
    "PURCHASED": "Silver"
  },
  {
    "id": 119024,
    "address": "2852 ORCHID ST",
    "city": "Ulen",
    "DOB": "1989-02-08T22:11:38Z",
    "sex": "M",
    "latitude": 47,
    "name": "JENNINGS, MICH,ARIAS D",
    "state": "Minnesota",
    "email": "",
    "longitude": -96,
    "EMPLOYMENT_STATUS": "Unemployed",
    "collection_id": "V_Participant_detail",
    "PEOPLE_COVERED": 1,
    "OPTIONAL_INSURED": 900000,
    "ANNUAL_INCOME": 100000,
    "MARITAL_STATUS": "M",
    "HEIGHT": 62,
    "WEIGHT": 197,
    "TOBACCO": "No",
    "GOLD": 106,
    "BRONZE": 41,
    "SILVER": 67,
    "PLATINUM": 158,
    "PURCHASED": "Silver"
  },
  {
    "id": 119026,
    "address": "425 DAHLIA TERR",
    "city": "Clearbrook",
    "DOB": "1989-09-08T22:11:38Z",
    "sex": "M",
    "latitude": 48,
    "name": "BARCANCEL,ANJOLEENA L",
    "state": "Minnesota",
    "email": "sstanfordrights@gmail.com",
    "longitude": -95,
    "EMPLOYMENT_STATUS": "Unemployed",
    "collection_id": "V_Participant_detail",
    "PEOPLE_COVERED": 1,
    "OPTIONAL_INSURED": 600000,
    "ANNUAL_INCOME": 300000,
    "MARITAL_STATUS": "S",
    "HEIGHT": 64,
    "WEIGHT": 138,
    "TOBACCO": "No",
    "GOLD": 98,
    "BRONZE": 33,
    "SILVER": 59,
    "PLATINUM": 150,
    "PURCHASED": "Silver"
  },
  {
    "id": 119036,
    "address": "680 SONOMA MOUNTAIN PKWY.",
    "city": "Windom",
    "DOB": "1989-11-08T22:11:38Z",
    "sex": "M",
    "latitude": 44,
    "name": "BALE,TAYREE E",
    "state": "Minnesota",
    "email": "",
    "longitude": -95,
    "EMPLOYMENT_STATUS": "Unemployed",
    "collection_id": "V_Participant_detail",
    "PEOPLE_COVERED": 3,
    "OPTIONAL_INSURED": 600000,
    "ANNUAL_INCOME": 400000,
    "MARITAL_STATUS": "M",
    "HEIGHT": 60,
    "WEIGHT": 259,
    "TOBACCO": "No",
    "GOLD": 103,
    "BRONZE": 38,
    "SILVER": 64,
    "PLATINUM": 155,
    "PURCHASED": "Silver"
  },
  {
    "id": 119054,
    "address": "1003 LONI DRIVE",
    "city": "Merrifield",
    "DOB": "1991-05-08T22:11:38Z",
    "sex": "M",
    "latitude": 47,
    "name": "CALANCHE,MARCO JR M",
    "state": "Minnesota",
    "email": "",
    "longitude": -94,
    "EMPLOYMENT_STATUS": "Unemployed",
    "collection_id": "V_Participant_detail",
    "PEOPLE_COVERED": 3,
    "OPTIONAL_INSURED": 600000,
    "ANNUAL_INCOME": 300000,
    "MARITAL_STATUS": "S",
    "HEIGHT": 79,
    "WEIGHT": 186,
    "TOBACCO": "No",
    "GOLD": 103,
    "BRONZE": 38,
    "SILVER": 64,
    "PLATINUM": 155,
    "PURCHASED": "Silver"
  },
  {
    "id": 119066,
    "address": "853 BEDFORD DRIVE",
    "city": "Inver Grove Heights",
    "DOB": "1991-01-08T22:11:38Z",
    "sex": "M",
    "latitude": 45,
    "name": "RINGER,RAVIAN L",
    "state": "Minnesota",
    "email": "MJMIKE1880@AOL.COM",
    "longitude": -93,
    "EMPLOYMENT_STATUS": "Unemployed",
    "collection_id": "V_Participant_detail",
    "PEOPLE_COVERED": 1,
    "OPTIONAL_INSURED": 800000,
    "ANNUAL_INCOME": 200000,
    "MARITAL_STATUS": "M",
    "HEIGHT": 51,
    "WEIGHT": 207,
    "TOBACCO": "Yes",
    "GOLD": 119,
    "BRONZE": 54,
    "SILVER": 80,
    "PLATINUM": 171,
    "PURCHASED": "Silver"
  },
  {
    "id": 119068,
    "address": "1809 AUTUMN WAY",
    "city": "Saint Paul",
    "DOB": "1991-06-08T22:11:38Z",
    "sex": "M",
    "latitude": 45,
    "name": "CATARROVA,MARIAHA D",
    "state": "Minnesota",
    "email": "",
    "longitude": -93,
    "EMPLOYMENT_STATUS": "Unemployed",
    "collection_id": "V_Participant_detail",
    "PEOPLE_COVERED": 1,
    "OPTIONAL_INSURED": 500000,
    "ANNUAL_INCOME": 200000,
    "MARITAL_STATUS": "M",
    "HEIGHT": 62,
    "WEIGHT": 112,
    "TOBACCO": "No",
    "GOLD": 96,
    "BRONZE": 31,
    "SILVER": 57,
    "PLATINUM": 148,
    "PURCHASED": "Silver"
  },
  {
    "id": 119083,
    "address": "682 HIGH ST",
    "city": "Alexandria",
    "DOB": "1991-01-08T22:11:38Z",
    "sex": "F",
    "latitude": 46,
    "name": "SHELNUTT-BORSO,LAKHVIR B",
    "state": "Minnesota",
    "email": "",
    "longitude": -95,
    "EMPLOYMENT_STATUS": "Unemployed",
    "collection_id": "V_Participant_detail",
    "PEOPLE_COVERED": 1,
    "OPTIONAL_INSURED": 800000,
    "ANNUAL_INCOME": 1000000,
    "MARITAL_STATUS": "M",
    "HEIGHT": 52,
    "WEIGHT": 190,
    "TOBACCO": "No",
    "GOLD": 103,
    "BRONZE": 38,
    "SILVER": 64,
    "PLATINUM": 155,
    "PURCHASED": "Silver"
  },
  {
    "id": 119093,
    "address": "5249 WINDINGWAY #10",
    "city": "Blue Earth",
    "DOB": "1989-10-08T22:11:38Z",
    "sex": "F",
    "latitude": 44,
    "name": "PROENCA,HONEY R",
    "state": "Minnesota",
    "email": "",
    "longitude": -94,
    "EMPLOYMENT_STATUS": "Unemployed",
    "collection_id": "V_Participant_detail",
    "PEOPLE_COVERED": 1,
    "OPTIONAL_INSURED": 800000,
    "ANNUAL_INCOME": 100000,
    "MARITAL_STATUS": "S",
    "HEIGHT": 64,
    "WEIGHT": 101,
    "TOBACCO": "No",
    "GOLD": 103,
    "BRONZE": 38,
    "SILVER": 64,
    "PLATINUM": 155,
    "PURCHASED": "Silver"
  },
  {
    "id": 119128,
    "address": "149 LEE ST #3",
    "city": "Cannon Falls",
    "DOB": "1990-06-08T22:11:38Z",
    "sex": "M",
    "latitude": 44,
    "name": "BARRERA RODRIGUEZ,PUCKETT J",
    "state": "Minnesota",
    "email": "",
    "longitude": -93,
    "EMPLOYMENT_STATUS": "Unemployed",
    "collection_id": "V_Participant_detail",
    "PEOPLE_COVERED": 4,
    "OPTIONAL_INSURED": 600000,
    "ANNUAL_INCOME": 100000,
    "MARITAL_STATUS": "M",
    "HEIGHT": 68,
    "WEIGHT": 181,
    "TOBACCO": "Yes",
    "GOLD": 122,
    "BRONZE": 57,
    "SILVER": 83,
    "PLATINUM": 174,
    "PURCHASED": "Silver"
  },
  {
    "id": 119132,
    "address": "3175 E WASHINGTON AVE",
    "city": "Red Wing",
    "DOB": "1989-04-08T22:11:38Z",
    "sex": "M",
    "latitude": 45,
    "name": "VIUST,STEN",
    "state": "Minnesota",
    "email": "",
    "longitude": -93,
    "EMPLOYMENT_STATUS": "Unemployed",
    "collection_id": "V_Participant_detail",
    "PEOPLE_COVERED": 1,
    "OPTIONAL_INSURED": 900000,
    "ANNUAL_INCOME": 100000,
    "MARITAL_STATUS": "M",
    "HEIGHT": 50,
    "WEIGHT": 110,
    "TOBACCO": "Yes",
    "GOLD": 122,
    "BRONZE": 57,
    "SILVER": 83,
    "PLATINUM": 174,
    "PURCHASED": "Silver"
  },
  {
    "id": 119134,
    "address": "2052 SILVER LAKE WY",
    "city": "Kenyon",
    "DOB": "1990-06-08T22:11:38Z",
    "sex": "M",
    "latitude": 44,
    "name": "CONCANNON-SLON,LA TANGERIA M",
    "state": "Minnesota",
    "email": "",
    "longitude": -93,
    "EMPLOYMENT_STATUS": "Unemployed",
    "collection_id": "V_Participant_detail",
    "PEOPLE_COVERED": 3,
    "OPTIONAL_INSURED": 700000,
    "ANNUAL_INCOME": 200000,
    "MARITAL_STATUS": "M",
    "HEIGHT": 62,
    "WEIGHT": 154,
    "TOBACCO": "Yes",
    "GOLD": 127,
    "BRONZE": 62,
    "SILVER": 88,
    "PLATINUM": 179,
    "PURCHASED": "Silver"
  },
  {
    "id": 119139,
    "address": "3504 WILLIAMS R",
    "city": "Norcross",
    "DOB": "1990-09-08T22:11:38Z",
    "sex": "F",
    "latitude": 46,
    "name": "JOSOL,SHAMONE C",
    "state": "Minnesota",
    "email": "",
    "longitude": -96,
    "EMPLOYMENT_STATUS": "Unemployed",
    "collection_id": "V_Participant_detail",
    "PEOPLE_COVERED": 3,
    "OPTIONAL_INSURED": 500000,
    "ANNUAL_INCOME": 300000,
    "MARITAL_STATUS": "S",
    "HEIGHT": 76,
    "WEIGHT": 246,
    "TOBACCO": "No",
    "GOLD": 96,
    "BRONZE": 31,
    "SILVER": 57,
    "PLATINUM": 148,
    "PURCHASED": "Gold"
  },
  {
    "id": 119154,
    "address": "2405-1C VIA MARIPOSA W.",
    "city": "Eden Prairie",
    "DOB": "1990-05-08T22:11:38Z",
    "sex": "M",
    "latitude": 45,
    "name": "CUMBELICH,RAVINDER J",
    "state": "Minnesota",
    "email": "",
    "longitude": -93,
    "EMPLOYMENT_STATUS": "Unemployed",
    "collection_id": "V_Participant_detail",
    "PEOPLE_COVERED": 3,
    "OPTIONAL_INSURED": 500000,
    "ANNUAL_INCOME": 100000,
    "MARITAL_STATUS": "M",
    "HEIGHT": 62,
    "WEIGHT": 192,
    "TOBACCO": "No",
    "GOLD": 96,
    "BRONZE": 31,
    "SILVER": 57,
    "PLATINUM": 148,
    "PURCHASED": "Silver"
  },
  {
    "id": 119167,
    "address": "1701 MARSHALL #292",
    "city": "Spring Park",
    "DOB": "1988-12-08T22:11:38Z",
    "sex": "F",
    "latitude": 45,
    "name": "VOLEK,JAMIL T",
    "state": "Minnesota",
    "email": "",
    "longitude": -94,
    "EMPLOYMENT_STATUS": "Unemployed",
    "collection_id": "V_Participant_detail",
    "PEOPLE_COVERED": 1,
    "OPTIONAL_INSURED": 500000,
    "ANNUAL_INCOME": 100000,
    "MARITAL_STATUS": "M",
    "HEIGHT": 58,
    "WEIGHT": 206,
    "TOBACCO": "No",
    "GOLD": 96,
    "BRONZE": 31,
    "SILVER": 57,
    "PLATINUM": 148,
    "PURCHASED": "Gold"
  },
  {
    "id": 119173,
    "address": "1 SARGENT STREET",
    "city": "Minneapolis",
    "DOB": "1991-11-08T22:11:38Z",
    "sex": "F",
    "latitude": 45,
    "name": "BOSKE,AULTON D",
    "state": "Minnesota",
    "email": "",
    "longitude": -93,
    "EMPLOYMENT_STATUS": "Unemployed",
    "collection_id": "V_Participant_detail",
    "PEOPLE_COVERED": 1,
    "OPTIONAL_INSURED": 500000,
    "ANNUAL_INCOME": 200000,
    "MARITAL_STATUS": "M",
    "HEIGHT": 69,
    "WEIGHT": 137,
    "TOBACCO": "Yes",
    "GOLD": 112,
    "BRONZE": 47,
    "SILVER": 73,
    "PLATINUM": 164,
    "PURCHASED": "Silver"
  },
  {
    "id": 119175,
    "address": "23521 PASEO DE VALENCIA",
    "city": "Minneapolis",
    "DOB": "1991-02-08T22:11:38Z",
    "sex": "F",
    "latitude": 45,
    "name": "SCHENEWARK,SKY R",
    "state": "Minnesota",
    "email": "",
    "longitude": -93,
    "EMPLOYMENT_STATUS": "Unemployed",
    "collection_id": "V_Participant_detail",
    "PEOPLE_COVERED": 2,
    "OPTIONAL_INSURED": 800000,
    "ANNUAL_INCOME": 700000,
    "MARITAL_STATUS": "M",
    "HEIGHT": 63,
    "WEIGHT": 168,
    "TOBACCO": "No",
    "GOLD": 111,
    "BRONZE": 46,
    "SILVER": 72,
    "PLATINUM": 163,
    "PURCHASED": "Silver"
  },
  {
    "id": 119178,
    "address": "1993 GALBRETH R",
    "city": "Minneapolis",
    "DOB": "1989-08-08T22:11:38Z",
    "sex": "M",
    "latitude": 45,
    "name": "SPIROCK,DEIJAH",
    "state": "Minnesota",
    "email": "",
    "longitude": -93,
    "EMPLOYMENT_STATUS": "Unemployed",
    "collection_id": "V_Participant_detail",
    "PEOPLE_COVERED": 1,
    "OPTIONAL_INSURED": 800000,
    "ANNUAL_INCOME": 300000,
    "MARITAL_STATUS": "S",
    "HEIGHT": 65,
    "WEIGHT": 163,
    "TOBACCO": "No",
    "GOLD": 103,
    "BRONZE": 38,
    "SILVER": 64,
    "PLATINUM": 155,
    "PURCHASED": "Silver"
  },
  {
    "id": 119190,
    "address": "15735 HAWTHORNE BLVD #111",
    "city": "Minneapolis",
    "DOB": "1990-09-08T22:11:38Z",
    "sex": "M",
    "latitude": 45,
    "name": "UWEKOOLANI,ALYSHYIA",
    "state": "Minnesota",
    "email": "",
    "longitude": -93,
    "EMPLOYMENT_STATUS": "Unemployed",
    "collection_id": "V_Participant_detail",
    "PEOPLE_COVERED": 2,
    "OPTIONAL_INSURED": 700000,
    "ANNUAL_INCOME": 200000,
    "MARITAL_STATUS": "S",
    "HEIGHT": 54,
    "WEIGHT": 107,
    "TOBACCO": "No",
    "GOLD": 106,
    "BRONZE": 41,
    "SILVER": 67,
    "PLATINUM": 158,
    "PURCHASED": "Silver"
  },
  {
    "id": 119218,
    "address": "2770 NEWHALL ST #23",
    "city": "Minneapolis",
    "DOB": "1989-07-08T22:11:38Z",
    "sex": "M",
    "latitude": 45,
    "name": "TORELLI,CHARLIE JR G",
    "state": "Minnesota",
    "email": "",
    "longitude": -93,
    "EMPLOYMENT_STATUS": "Unemployed",
    "collection_id": "V_Participant_detail",
    "PEOPLE_COVERED": 2,
    "OPTIONAL_INSURED": 500000,
    "ANNUAL_INCOME": 300000,
    "MARITAL_STATUS": "M",
    "HEIGHT": 62,
    "WEIGHT": 138,
    "TOBACCO": "No",
    "GOLD": 96,
    "BRONZE": 31,
    "SILVER": 57,
    "PLATINUM": 148,
    "PURCHASED": "Gold"
  },
  {
    "id": 119251,
    "address": "2201 WEBSTER ST",
    "city": "Eitzen",
    "DOB": "1991-01-08T22:11:38Z",
    "sex": "F",
    "latitude": 44,
    "name": "MECK,JUSTINS L",
    "state": "Minnesota",
    "email": "",
    "longitude": -91,
    "EMPLOYMENT_STATUS": "Unemployed",
    "collection_id": "V_Participant_detail",
    "PEOPLE_COVERED": 1,
    "OPTIONAL_INSURED": 700000,
    "ANNUAL_INCOME": 100000,
    "MARITAL_STATUS": "S",
    "HEIGHT": 54,
    "WEIGHT": 101,
    "TOBACCO": "Yes",
    "GOLD": 117,
    "BRONZE": 52,
    "SILVER": 78,
    "PLATINUM": 169,
    "PURCHASED": "Silver"
  },
  {
    "id": 119260,
    "address": "",
    "city": "Wells",
    "DOB": "1990-05-08T22:11:38Z",
    "sex": "M",
    "latitude": 41,
    "name": "LU SR.,TAI ANTHON S",
    "state": "Nevada",
    "email": "",
    "longitude": -115,
    "EMPLOYMENT_STATUS": "Unemployed",
    "collection_id": "V_Participant_detail",
    "PEOPLE_COVERED": 4,
    "OPTIONAL_INSURED": 600000,
    "ANNUAL_INCOME": 200000,
    "MARITAL_STATUS": "M",
    "HEIGHT": 79,
    "WEIGHT": 171,
    "TOBACCO": "No",
    "GOLD": 106,
    "BRONZE": 41,
    "SILVER": 67,
    "PLATINUM": 158,
    "PURCHASED": "Silver"
  },
  {
    "id": 119298,
    "address": "7887 SOQUEL DRIVE",
    "city": "Pahrump",
    "DOB": "1990-07-08T22:11:38Z",
    "sex": "M",
    "latitude": 36,
    "name": "CARIG,TYTUS",
    "state": "Nevada",
    "email": "",
    "longitude": -116,
    "EMPLOYMENT_STATUS": "Unemployed",
    "collection_id": "V_Participant_detail",
    "PEOPLE_COVERED": 4,
    "OPTIONAL_INSURED": 500000,
    "ANNUAL_INCOME": 700000,
    "MARITAL_STATUS": "M",
    "HEIGHT": 56,
    "WEIGHT": 232,
    "TOBACCO": "No",
    "GOLD": 96,
    "BRONZE": 31,
    "SILVER": 57,
    "PLATINUM": 148,
    "PURCHASED": "Gold"
  },
  {
    "id": 119300,
    "address": "8043 MITCHELL DR",
    "city": "Pahrump",
    "DOB": "1990-02-08T22:11:38Z",
    "sex": "M",
    "latitude": 36,
    "name": "ROCKSANNE,CHAKWAH",
    "state": "Nevada",
    "email": "",
    "longitude": -116,
    "EMPLOYMENT_STATUS": "Unemployed",
    "collection_id": "V_Participant_detail",
    "PEOPLE_COVERED": 1,
    "OPTIONAL_INSURED": 800000,
    "ANNUAL_INCOME": 300000,
    "MARITAL_STATUS": "M",
    "HEIGHT": 71,
    "WEIGHT": 101,
    "TOBACCO": "No",
    "GOLD": 103,
    "BRONZE": 38,
    "SILVER": 64,
    "PLATINUM": 155,
    "PURCHASED": "Gold"
  },
  {
    "id": 119319,
    "address": "1144 CONROY LN #J",
    "city": "Sparks",
    "DOB": "1989-06-08T22:11:38Z",
    "sex": "F",
    "latitude": 40,
    "name": "NGOW,FARUKH L",
    "state": "Nevada",
    "email": "",
    "longitude": -120,
    "EMPLOYMENT_STATUS": "Unemployed",
    "collection_id": "V_Participant_detail",
    "PEOPLE_COVERED": 3,
    "OPTIONAL_INSURED": 500000,
    "ANNUAL_INCOME": 100000,
    "MARITAL_STATUS": "S",
    "HEIGHT": 64,
    "WEIGHT": 102,
    "TOBACCO": "Yes",
    "GOLD": 112,
    "BRONZE": 47,
    "SILVER": 73,
    "PLATINUM": 164,
    "PURCHASED": "Silver"
  },
  {
    "id": 119327,
    "address": "P O BOX 1787",
    "city": "Reno",
    "DOB": "1989-09-08T22:11:38Z",
    "sex": "F",
    "latitude": 40,
    "name": "NOORZAI,AMNESTY M",
    "state": "Nevada",
    "email": "",
    "longitude": -120,
    "EMPLOYMENT_STATUS": "Unemployed",
    "collection_id": "V_Participant_detail",
    "PEOPLE_COVERED": 2,
    "OPTIONAL_INSURED": 800000,
    "ANNUAL_INCOME": 200000,
    "MARITAL_STATUS": "M",
    "HEIGHT": 74,
    "WEIGHT": 113,
    "TOBACCO": "No",
    "GOLD": 111,
    "BRONZE": 46,
    "SILVER": 72,
    "PLATINUM": 163,
    "PURCHASED": "Silver"
  },
  {
    "id": 119336,
    "address": "1138 RACHEL RD",
    "city": "Reno",
    "DOB": "1991-04-08T22:11:38Z",
    "sex": "M",
    "latitude": 40,
    "name": "SIERRA JR,SHANXIN J",
    "state": "Nevada",
    "email": "",
    "longitude": -120,
    "EMPLOYMENT_STATUS": "Unemployed",
    "collection_id": "V_Participant_detail",
    "PEOPLE_COVERED": 1,
    "OPTIONAL_INSURED": 800000,
    "ANNUAL_INCOME": 100000,
    "MARITAL_STATUS": "M",
    "HEIGHT": 65,
    "WEIGHT": 100,
    "TOBACCO": "No",
    "GOLD": 103,
    "BRONZE": 38,
    "SILVER": 64,
    "PLATINUM": 155,
    "PURCHASED": "Silver"
  },
  {
    "id": 119339,
    "address": "2936 PEACHTREE DR",
    "city": "Reno",
    "DOB": "1990-03-08T22:11:38Z",
    "sex": "F",
    "latitude": 40,
    "name": "LONGENECKER,CHONTELLE G",
    "state": "Nevada",
    "email": "",
    "longitude": -120,
    "EMPLOYMENT_STATUS": "Unemployed",
    "collection_id": "V_Participant_detail",
    "PEOPLE_COVERED": 1,
    "OPTIONAL_INSURED": 500000,
    "ANNUAL_INCOME": 200000,
    "MARITAL_STATUS": "M",
    "HEIGHT": 64,
    "WEIGHT": 207,
    "TOBACCO": "No",
    "GOLD": 96,
    "BRONZE": 31,
    "SILVER": 57,
    "PLATINUM": 148,
    "PURCHASED": "Silver"
  },
  {
    "id": 119361,
    "address": "15885 FAITH PLACE",
    "city": "Carson City",
    "DOB": "1991-10-08T22:11:38Z",
    "sex": "F",
    "latitude": 39,
    "name": "GOLDFARB,SIBHAN M",
    "state": "Nevada",
    "email": "",
    "longitude": -120,
    "EMPLOYMENT_STATUS": "Unemployed",
    "collection_id": "V_Participant_detail",
    "PEOPLE_COVERED": 1,
    "OPTIONAL_INSURED": 500000,
    "ANNUAL_INCOME": 200000,
    "MARITAL_STATUS": "M",
    "HEIGHT": 50,
    "WEIGHT": 163,
    "TOBACCO": "Yes",
    "GOLD": 112,
    "BRONZE": 47,
    "SILVER": 73,
    "PLATINUM": 164,
    "PURCHASED": "Silver"
  },
  {
    "id": 119366,
    "address": "FBO Ingrid Williams #R30589",
    "city": "Bridgeport",
    "DOB": "1991-03-08T22:11:38Z",
    "sex": "M",
    "latitude": 44,
    "name": "THACK,JANECE R",
    "state": "Oregon",
    "email": "",
    "longitude": -118,
    "EMPLOYMENT_STATUS": "Unemployed",
    "collection_id": "V_Participant_detail",
    "PEOPLE_COVERED": 1,
    "OPTIONAL_INSURED": 600000,
    "ANNUAL_INCOME": 700000,
    "MARITAL_STATUS": "M",
    "HEIGHT": 73,
    "WEIGHT": 171,
    "TOBACCO": "No",
    "GOLD": 98,
    "BRONZE": 33,
    "SILVER": 59,
    "PLATINUM": 150,
    "PURCHASED": "Silver"
  },
  {
    "id": 119373,
    "address": "10539 S BLANEY",
    "city": "Unity",
    "DOB": "1989-02-08T22:11:38Z",
    "sex": "F",
    "latitude": 44,
    "name": "ARRIIOLA III,CHRISTYANN L",
    "state": "Oregon",
    "email": "",
    "longitude": -118,
    "EMPLOYMENT_STATUS": "Unemployed",
    "collection_id": "V_Participant_detail",
    "PEOPLE_COVERED": 1,
    "OPTIONAL_INSURED": 500000,
    "ANNUAL_INCOME": 100000,
    "MARITAL_STATUS": "M",
    "HEIGHT": 61,
    "WEIGHT": 114,
    "TOBACCO": "No",
    "GOLD": 96,
    "BRONZE": 31,
    "SILVER": 57,
    "PLATINUM": 148,
    "PURCHASED": "Silver"
  },
  {
    "id": 119382,
    "address": "5113 JAMES AVE",
    "city": "Philomath",
    "DOB": "1991-03-08T22:11:38Z",
    "sex": "M",
    "latitude": 45,
    "name": "DELACY,ZULMA S",
    "state": "Oregon",
    "email": "",
    "longitude": -123,
    "EMPLOYMENT_STATUS": "Unemployed",
    "collection_id": "V_Participant_detail",
    "PEOPLE_COVERED": 1,
    "OPTIONAL_INSURED": 500000,
    "ANNUAL_INCOME": 100000,
    "MARITAL_STATUS": "S",
    "HEIGHT": 72,
    "WEIGHT": 257,
    "TOBACCO": "No",
    "GOLD": 96,
    "BRONZE": 31,
    "SILVER": 57,
    "PLATINUM": 148,
    "PURCHASED": "Silver"
  },
  {
    "id": 119387,
    "address": "760-A   TAMALPIAS AVE",
    "city": "Canby",
    "DOB": "1989-09-08T22:11:38Z",
    "sex": "F",
    "latitude": 45,
    "name": "PHILANDER,AGHA R",
    "state": "Oregon",
    "email": "",
    "longitude": -123,
    "EMPLOYMENT_STATUS": "Unemployed",
    "collection_id": "V_Participant_detail",
    "PEOPLE_COVERED": 1,
    "OPTIONAL_INSURED": 800000,
    "ANNUAL_INCOME": 100000,
    "MARITAL_STATUS": "S",
    "HEIGHT": 63,
    "WEIGHT": 116,
    "TOBACCO": "No",
    "GOLD": 103,
    "BRONZE": 38,
    "SILVER": 64,
    "PLATINUM": 155,
    "PURCHASED": "Silver"
  }
]
}